{
  "player": 0,
  "street": 0,
  "children": 2,
  "sequence": [
    {
      "player": 0,
      "type": "R",
      "amount": 2500
    },
    {
      "player": 1,
      "type": "R",
      "amount": 7500
    },
    {
      "player": 2,
      "type": "F",
      "amount": 0
    },
    {
      "player": 3,
      "type": "F",
      "amount": 0
    },
    {
      "player": 4,
      "type": "F",
      "amount": 0
    },
    {
      "player": 5,
      "type": "F",
      "amount": 0
    },
    {
      "player": 0,
      "type": "R",
      "amount": 25000
    },
    {
      "player": 1,
      "type": "R",
      "amount": 100000
    }
  ],
  "actions": [
    {
      "type": "F",
      "amount": 0
    },
    {
      "type": "C",
      "amount": 75000
    }
  ],
  "hands": {
    "22": {
      "weight": 0.0,
      "played": [
        1.0,
        0.0
      ],
      "evs": [
        0.0,
        -3.9491
      ]
    },
    "32o": {
      "weight": 0.0,
      "played": [
        1.0,
        0.0
      ],
      "evs": [
        0.0,
        -26.84867
      ]
    },
    "42o": {
      "weight": 0.0,
      "played": [
        1.0,
        0.0
      ],
      "evs": [
        0.0,
        -26.1417
      ]
    },
    "52o": {
      "weight": 0.0,
      "played": [
        1.0,
        0.0
      ],
      "evs": [
        0.0,
        -25.08666
      ]
    },
    "62o": {
      "weight": 0.0,
      "played": [
        1.0,
        0.0
      ],
      "evs": [
        0.0,
        -27.7241
      ]
    },
    "72o": {
      "weight": 0.0,
      "played": [
        1.0,
        0.0
      ],
      "evs": [
        0.0,
        -30.27728
      ]
    },
    "82o": {
      "weight": 0.0,
      "played": [
        1.0,
        0.0
      ],
      "evs": [
        0.0,
        -30.22927
      ]
    },
    "92o": {
      "weight": 0.0,
      "played": [
        1.0,
        0.0
      ],
      "evs": [
        0.0,
        -30.69437
      ]
    },
    "T2o": {
      "weight": 0.0,
      "played": [
        1.0,
        0.0
      ],
      "evs": [
        0.0,
        -30.89916
      ]
    },
    "J2o": {
      "weight": 0.0,
      "played": [
        1.0,
        0.0
      ],
      "evs": [
        0.0,
        -31.4225
      ]
    },
    "Q2o": {
      "weight": 0.0,
      "played": [
        1.0,
        0.0
      ],
      "evs": [
        0.0,
        -30.82471
      ]
    },
    "K2o": {
      "weight": 0.0,
      "played": [
        1.0,
        0.0
      ],
      "evs": [
        0.0,
        -41.15379
      ]
    },
    "A2o": {
      "weight": 0.0,
      "played": [
        1.0,
        0.0
      ],
      "evs": [
        0.0,
        -24.63077
      ]
    },
    "32s": {
      "weight": 0.0,
      "played": [
        1.0,
        0.0
      ],
      "evs": [
        0.0,
        -19.33397
      ]
    },
    "33": {
      "weight": 0.0,
      "played": [
        1.0,
        0.0
      ],
      "evs": [
        0.0,
        -2.75817
      ]
    },
    "43o": {
      "weight": 0.0,
      "played": [
        1.0,
        0.0
      ],
      "evs": [
        0.0,
        -22.98391
      ]
    },
    "53o": {
      "weight": 0.0,
      "played": [
        1.0,
        0.0
      ],
      "evs": [
        0.0,
        -22.0237
      ]
    },
    "63o": {
      "weight": 0.0,
      "played": [
        1.0,
        0.0
      ],
      "evs": [
        0.0,
        -24.55932
      ]
    },
    "73o": {
      "weight": 0.0,
      "played": [
        1.0,
        0.0
      ],
      "evs": [
        0.0,
        -27.1408
      ]
    },
    "83o": {
      "weight": 0.0,
      "played": [
        1.0,
        0.0
      ],
      "evs": [
        0.0,
        -30.21886
      ]
    },
    "93o": {
      "weight": 0.0,
      "played": [
        1.0,
        0.0
      ],
      "evs": [
        0.0,
        -30.024
      ]
    },
    "T3o": {
      "weight": 0.0,
      "played": [
        1.0,
        0.0
      ],
      "evs": [
        0.0,
        -30.25164
      ]
    },
    "J3o": {
      "weight": 0.0,
      "played": [
        1.0,
        0.0
      ],
      "evs": [
        0.0,
        -30.55139
      ]
    },
    "Q3o": {
      "weight": 0.0,
      "played": [
        1.0,
        0.0
      ],
      "evs": [
        0.0,
        -29.89111
      ]
    },
    "K3o": {
      "weight": 0.0,
      "played": [
        1.0,
        0.0
      ],
      "evs": [
        0.0,
        -39.79093
      ]
    },
    "A3o": {
      "weight": 0.0,
      "played": [
        1.0,
        0.0
      ],
      "evs": [
        0.0,
        -23.59137
      ]
    },
    "42s": {
      "weight": 0.0,
      "played": [
        1.0,
        0.0
      ],
      "evs": [
        0.0,
        -18.58416
      ]
    },
    "43s": {
      "weight": 0.0,
      "played": [
        1.0,
        0.0
      ],
      "evs": [
        0.0,
        -15.82498
      ]
    },
    "44": {
      "weight": 0.0,
      "played": [
        1.0,
        0.0
      ],
      "evs": [
        0.0,
        -1.50788
      ]
    },
    "54o": {
      "weight": 0.0,
      "played": [
        1.0,
        0.0
      ],
      "evs": [
        0.0,
        -19.12257
      ]
    },
    "64o": {
      "weight": 0.0,
      "played": [
        1.0,
        0.0
      ],
      "evs": [
        0.0,
        -21.83345
      ]
    },
    "74o": {
      "weight": 0.0,
      "played": [
        1.0,
        0.0
      ],
      "evs": [
        0.0,
        -24.41235
      ]
    },
    "84o": {
      "weight": 0.0,
      "played": [
        1.0,
        0.0
      ],
      "evs": [
        0.0,
        -27.18881
      ]
    },
    "94o": {
      "weight": 0.0,
      "played": [
        1.0,
        0.0
      ],
      "evs": [
        0.0,
        -29.93318
      ]
    },
    "T4o": {
      "weight": 0.0,
      "played": [
        1.0,
        0.0
      ],
      "evs": [
        0.0,
        -29.12757
      ]
    },
    "J4o": {
      "weight": 0.0,
      "played": [
        1.0,
        0.0
      ],
      "evs": [
        0.0,
        -29.69354
      ]
    },
    "Q4o": {
      "weight": 0.0,
      "played": [
        1.0,
        0.0
      ],
      "evs": [
        0.0,
        -28.59136
      ]
    },
    "K4o": {
      "weight": 0.0,
      "played": [
        1.0,
        0.0
      ],
      "evs": [
        0.0,
        -39.03009
      ]
    },
    "A4o": {
      "weight": 0.0,
      "played": [
        1.0,
        0.0
      ],
      "evs": [
        0.0,
        -22.81028
      ]
    },
    "52s": {
      "weight": 0.0,
      "played": [
        1.0,
        0.0
      ],
      "evs": [
        0.0,
        -17.62357
      ]
    },
    "53s": {
      "weight": 0.0,
      "played": [
        1.0,
        0.0
      ],
      "evs": [
        0.0,
        -15.04021
      ]
    },
    "54s": {
      "weight": 0.0,
      "played": [
        1.0,
        0.0
      ],
      "evs": [
        0.0,
        -12.05505
      ]
    },
    "55": {
      "weight": 0.0,
      "played": [
        0.9918,
        0.0082
      ],
      "evs": [
        0.0,
        -0.85789
      ]
    },
    "65o": {
      "weight": 0.0,
      "played": [
        1.0,
        0.0
      ],
      "evs": [
        0.0,
        -18.23238
      ]
    },
    "75o": {
      "weight": 0.0,
      "played": [
        1.0,
        0.0
      ],
      "evs": [
        0.0,
        -21.05857
      ]
    },
    "85o": {
      "weight": 0.0,
      "played": [
        1.0,
        0.0
      ],
      "evs": [
        0.0,
        -24.23252
      ]
    },
    "95o": {
      "weight": 0.0,
      "played": [
        1.0,
        0.0
      ],
      "evs": [
        0.0,
        -26.76694
      ]
    },
    "T5o": {
      "weight": 0.0,
      "played": [
        1.0,
        0.0
      ],
      "evs": [
        0.0,
        -29.33502
      ]
    },
    "J5o": {
      "weight": 0.0,
      "played": [
        1.0,
        0.0
      ],
      "evs": [
        0.0,
        -29.09508
      ]
    },
    "Q5o": {
      "weight": 0.0,
      "played": [
        1.0,
        0.0
      ],
      "evs": [
        0.0,
        -28.15893
      ]
    },
    "K5o": {
      "weight": 0.0,
      "played": [
        1.0,
        0.0
      ],
      "evs": [
        0.0,
        -38.13901
      ]
    },
    "A5o": {
      "weight": 0.0,
      "played": [
        1.0,
        0.0
      ],
      "evs": [
        0.0,
        -21.53255
      ]
    },
    "62s": {
      "weight": 0.0,
      "played": [
        1.0,
        0.0
      ],
      "evs": [
        0.0,
        -20.21534
      ]
    },
    "63s": {
      "weight": 0.0,
      "played": [
        1.0,
        0.0
      ],
      "evs": [
        0.0,
        -16.90152
      ]
    },
    "64s": {
      "weight": 0.0,
      "played": [
        1.0,
        0.0
      ],
      "evs": [
        0.0,
        -14.03671
      ]
    },
    "65s": {
      "weight": 0.0,
      "played": [
        1.0,
        0.0
      ],
      "evs": [
        0.0,
        -11.37245
      ]
    },
    "66": {
      "weight": 0.0,
      "played": [
        0.9172,
        0.0828
      ],
      "evs": [
        0.0,
        -0.32903
      ]
    },
    "76o": {
      "weight": 0.0,
      "played": [
        1.0,
        0.0
      ],
      "evs": [
        0.0,
        -18.21017
      ]
    },
    "86o": {
      "weight": 0.0,
      "played": [
        1.0,
        0.0
      ],
      "evs": [
        0.0,
        -21.27669
      ]
    },
    "96o": {
      "weight": 0.0,
      "played": [
        1.0,
        0.0
      ],
      "evs": [
        0.0,
        -24.02561
      ]
    },
    "T6o": {
      "weight": 0.0,
      "played": [
        1.0,
        0.0
      ],
      "evs": [
        0.0,
        -26.85477
      ]
    },
    "J6o": {
      "weight": 0.0,
      "played": [
        1.0,
        0.0
      ],
      "evs": [
        0.0,
        -29.23701
      ]
    },
    "Q6o": {
      "weight": 0.0,
      "played": [
        1.0,
        0.0
      ],
      "evs": [
        0.0,
        -27.96404
      ]
    },
    "K6o": {
      "weight": 0.0,
      "played": [
        1.0,
        0.0
      ],
      "evs": [
        0.0,
        -37.67141
      ]
    },
    "A6o": {
      "weight": 0.0,
      "played": [
        1.0,
        0.0
      ],
      "evs": [
        0.0,
        -24.72732
      ]
    },
    "72s": {
      "weight": 0.0,
      "played": [
        1.0,
        0.0
      ],
      "evs": [
        0.0,
        -22.53024
      ]
    },
    "73s": {
      "weight": 0.0,
      "played": [
        1.0,
        0.0
      ],
      "evs": [
        0.0,
        -19.70367
      ]
    },
    "74s": {
      "weight": 0.0,
      "played": [
        1.0,
        0.0
      ],
      "evs": [
        0.0,
        -16.59679
      ]
    },
    "75s": {
      "weight": 0.0,
      "played": [
        1.0,
        0.0
      ],
      "evs": [
        0.0,
        -13.77644
      ]
    },
    "76s": {
      "weight": 0.0105,
      "played": [
        1.0,
        0.0
      ],
      "evs": [
        0.0,
        -11.20615
      ]
    },
    "77": {
      "weight": 0.0554,
      "played": [
        0.8387,
        0.1613
      ],
      "evs": [
        0.0,
        -0.20061
      ]
    },
    "87o": {
      "weight": 0.0,
      "played": [
        1.0,
        0.0
      ],
      "evs": [
        0.0,
        -18.98431
      ]
    },
    "97o": {
      "weight": 0.0,
      "played": [
        1.0,
        0.0
      ],
      "evs": [
        0.0,
        -21.841
      ]
    },
    "T7o": {
      "weight": 0.0,
      "played": [
        1.0,
        0.0
      ],
      "evs": [
        0.0,
        -24.38187
      ]
    },
    "J7o": {
      "weight": 0.0,
      "played": [
        1.0,
        0.0
      ],
      "evs": [
        0.0,
        -27.142
      ]
    },
    "Q7o": {
      "weight": 0.0,
      "played": [
        1.0,
        0.0
      ],
      "evs": [
        0.0,
        -28.45353
      ]
    },
    "K7o": {
      "weight": 0.0,
      "played": [
        1.0,
        0.0
      ],
      "evs": [
        0.0,
        -37.62883
      ]
    },
    "A7o": {
      "weight": 0.0,
      "played": [
        1.0,
        0.0
      ],
      "evs": [
        0.0,
        -23.46095
      ]
    },
    "82s": {
      "weight": 0.0,
      "played": [
        1.0,
        0.0
      ],
      "evs": [
        0.0,
        -22.42653
      ]
    },
    "83s": {
      "weight": 0.0,
      "played": [
        1.0,
        0.0
      ],
      "evs": [
        0.0,
        -22.20732
      ]
    },
    "84s": {
      "weight": 0.0,
      "played": [
        1.0,
        0.0
      ],
      "evs": [
        0.0,
        -19.25842
      ]
    },
    "85s": {
      "weight": 0.0,
      "played": [
        1.0,
        0.0
      ],
      "evs": [
        0.0,
        -16.14763
      ]
    },
    "86s": {
      "weight": 0.0,
      "played": [
        1.0,
        0.0
      ],
      "evs": [
        0.0,
        -13.77331
      ]
    },
    "87s": {
      "weight": 0.0,
      "played": [
        1.0,
        0.0
      ],
      "evs": [
        0.0,
        -11.69764
      ]
    },
    "88": {
      "weight": 0.042,
      "played": [
        0.8329,
        0.1671
      ],
      "evs": [
        0.0,
        -0.04558
      ]
    },
    "98o": {
      "weight": 0.0,
      "played": [
        1.0,
        0.0
      ],
      "evs": [
        0.0,
        -21.24655
      ]
    },
    "T8o": {
      "weight": 0.0,
      "played": [
        1.0,
        0.0
      ],
      "evs": [
        0.0,
        -22.1899
      ]
    },
    "J8o": {
      "weight": 0.0,
      "played": [
        1.0,
        0.0
      ],
      "evs": [
        0.0,
        -24.80847
      ]
    },
    "Q8o": {
      "weight": 0.0,
      "played": [
        1.0,
        0.0
      ],
      "evs": [
        0.0,
        -26.39744
      ]
    },
    "K8o": {
      "weight": 0.0,
      "played": [
        1.0,
        0.0
      ],
      "evs": [
        0.0,
        -38.36892
      ]
    },
    "A8o": {
      "weight": 0.0,
      "played": [
        1.0,
        0.0
      ],
      "evs": [
        0.0,
        -24.64596
      ]
    },
    "92s": {
      "weight": 0.0,
      "played": [
        1.0,
        0.0
      ],
      "evs": [
        0.0,
        -22.92426
      ]
    },
    "93s": {
      "weight": 0.0,
      "played": [
        1.0,
        0.0
      ],
      "evs": [
        0.0,
        -21.90311
      ]
    },
    "94s": {
      "weight": 0.0,
      "played": [
        1.0,
        0.0
      ],
      "evs": [
        0.0,
        -21.91551
      ]
    },
    "95s": {
      "weight": 0.0,
      "played": [
        1.0,
        0.0
      ],
      "evs": [
        0.0,
        -19.29813
      ]
    },
    "96s": {
      "weight": 0.0,
      "played": [
        1.0,
        0.0
      ],
      "evs": [
        0.0,
        -16.19534
      ]
    },
    "97s": {
      "weight": 0.0,
      "played": [
        1.0,
        0.0
      ],
      "evs": [
        0.0,
        -14.12863
      ]
    },
    "98s": {
      "weight": 0.0,
      "played": [
        1.0,
        0.0
      ],
      "evs": [
        0.0,
        -13.81596
      ]
    },
    "99": {
      "weight": 0.0302,
      "played": [
        0.8525,
        0.1475
      ],
      "evs": [
        0.0,
        -0.22875
      ]
    },
    "T9o": {
      "weight": 0.0,
      "played": [
        1.0,
        0.0
      ],
      "evs": [
        0.0,
        -20.72483
      ]
    },
    "J9o": {
      "weight": 0.0,
      "played": [
        1.0,
        0.0
      ],
      "evs": [
        0.0,
        -23.30479
      ]
    },
    "Q9o": {
      "weight": 0.0,
      "played": [
        1.0,
        0.0
      ],
      "evs": [
        0.0,
        -24.85011
      ]
    },
    "K9o": {
      "weight": 0.0,
      "played": [
        1.0,
        0.0
      ],
      "evs": [
        0.0,
        -37.32448
      ]
    },
    "A9o": {
      "weight": 0.0,
      "played": [
        1.0,
        0.0
      ],
      "evs": [
        0.0,
        -24.98635
      ]
    },
    "T2s": {
      "weight": 0.0,
      "played": [
        1.0,
        0.0
      ],
      "evs": [
        0.0,
        -23.19046
      ]
    },
    "T3s": {
      "weight": 0.0,
      "played": [
        1.0,
        0.0
      ],
      "evs": [
        0.0,
        -22.22928
      ]
    },
    "T4s": {
      "weight": 0.0,
      "played": [
        1.0,
        0.0
      ],
      "evs": [
        0.0,
        -21.01837
      ]
    },
    "T5s": {
      "weight": 0.0,
      "played": [
        1.0,
        0.0
      ],
      "evs": [
        0.0,
        -21.61483
      ]
    },
    "T6s": {
      "weight": 0.0,
      "played": [
        1.0,
        0.0
      ],
      "evs": [
        0.0,
        -19.07585
      ]
    },
    "T7s": {
      "weight": 0.0,
      "played": [
        1.0,
        0.0
      ],
      "evs": [
        0.0,
        -16.59636
      ]
    },
    "T8s": {
      "weight": 0.0,
      "played": [
        1.0,
        0.0
      ],
      "evs": [
        0.0,
        -14.83255
      ]
    },
    "T9s": {
      "weight": 0.0,
      "played": [
        1.0,
        0.0
      ],
      "evs": [
        0.0,
        -13.3851
      ]
    },
    "TT": {
      "weight": 0.0202,
      "played": [
        0.0192,
        0.9808
      ],
      "evs": [
        0.0,
        1.05384
      ]
    },
    "JTo": {
      "weight": 0.0,
      "played": [
        1.0,
        0.0
      ],
      "evs": [
        0.0,
        -21.20963
      ]
    },
    "QTo": {
      "weight": 0.0,
      "played": [
        1.0,
        0.0
      ],
      "evs": [
        0.0,
        -22.66688
      ]
    },
    "KTo": {
      "weight": 0.0,
      "played": [
        1.0,
        0.0
      ],
      "evs": [
        0.0,
        -33.76989
      ]
    },
    "ATo": {
      "weight": 0.0,
      "played": [
        1.0,
        0.0
      ],
      "evs": [
        0.0,
        -23.45223
      ]
    },
    "J2s": {
      "weight": 0.0,
      "played": [
        1.0,
        0.0
      ],
      "evs": [
        0.0,
        -23.19333
      ]
    },
    "J3s": {
      "weight": 0.0,
      "played": [
        1.0,
        0.0
      ],
      "evs": [
        0.0,
        -22.43988
      ]
    },
    "J4s": {
      "weight": 0.0,
      "played": [
        1.0,
        0.0
      ],
      "evs": [
        0.0,
        -21.82053
      ]
    },
    "J5s": {
      "weight": 0.0,
      "played": [
        1.0,
        0.0
      ],
      "evs": [
        0.0,
        -21.4029
      ]
    },
    "J6s": {
      "weight": 0.0,
      "played": [
        1.0,
        0.0
      ],
      "evs": [
        0.0,
        -21.59762
      ]
    },
    "J7s": {
      "weight": 0.0,
      "played": [
        1.0,
        0.0
      ],
      "evs": [
        0.0,
        -19.46293
      ]
    },
    "J8s": {
      "weight": 0.0,
      "played": [
        1.0,
        0.0
      ],
      "evs": [
        0.0,
        -16.87856
      ]
    },
    "J9s": {
      "weight": 0.0,
      "played": [
        1.0,
        0.0
      ],
      "evs": [
        0.0,
        -15.88046
      ]
    },
    "JTs": {
      "weight": 0.0,
      "played": [
        1.0,
        0.0
      ],
      "evs": [
        0.0,
        -13.53604
      ]
    },
    "JJ": {
      "weight": 0.2101,
      "played": [
        0.0,
        1.0
      ],
      "evs": [
        0.0,
        3.72589
      ]
    },
    "QJo": {
      "weight": 0.0,
      "played": [
        1.0,
        0.0
      ],
      "evs": [
        0.0,
        -23.3211
      ]
    },
    "KJo": {
      "weight": 0.0,
      "played": [
        1.0,
        0.0
      ],
      "evs": [
        0.0,
        -35.16408
      ]
    },
    "AJo": {
      "weight": 0.0,
      "played": [
        1.0,
        0.0
      ],
      "evs": [
        0.0,
        -24.13881
      ]
    },
    "Q2s": {
      "weight": 0.0,
      "played": [
        1.0,
        0.0
      ],
      "evs": [
        0.0,
        -22.72363
      ]
    },
    "Q3s": {
      "weight": 0.0,
      "played": [
        1.0,
        0.0
      ],
      "evs": [
        0.0,
        -21.99412
      ]
    },
    "Q4s": {
      "weight": 0.0,
      "played": [
        1.0,
        0.0
      ],
      "evs": [
        0.0,
        -20.83105
      ]
    },
    "Q5s": {
      "weight": 0.0,
      "played": [
        1.0,
        0.0
      ],
      "evs": [
        0.0,
        -20.27514
      ]
    },
    "Q6s": {
      "weight": 0.0,
      "played": [
        1.0,
        0.0
      ],
      "evs": [
        0.0,
        -20.04033
      ]
    },
    "Q7s": {
      "weight": 0.0,
      "played": [
        1.0,
        0.0
      ],
      "evs": [
        0.0,
        -20.91128
      ]
    },
    "Q8s": {
      "weight": 0.0,
      "played": [
        1.0,
        0.0
      ],
      "evs": [
        0.0,
        -18.82754
      ]
    },
    "Q9s": {
      "weight": 0.0,
      "played": [
        1.0,
        0.0
      ],
      "evs": [
        0.0,
        -16.69383
      ]
    },
    "QTs": {
      "weight": 0.0,
      "played": [
        1.0,
        0.0
      ],
      "evs": [
        0.0,
        -15.3857
      ]
    },
    "QJs": {
      "weight": 0.0,
      "played": [
        1.0,
        0.0
      ],
      "evs": [
        0.0,
        -16.56359
      ]
    },
    "QQ": {
      "weight": 0.4136,
      "played": [
        0.0,
        1.0
      ],
      "evs": [
        0.0,
        7.8211
      ]
    },
    "KQo": {
      "weight": 3.0E-4,
      "played": [
        1.0,
        0.0
      ],
      "evs": [
        0.0,
        -33.0264
      ]
    },
    "AQo": {
      "weight": 0.5042,
      "played": [
        1.0,
        0.0
      ],
      "evs": [
        0.0,
        -22.86593
      ]
    },
    "K2s": {
      "weight": 0.0,
      "played": [
        1.0,
        0.0
      ],
      "evs": [
        0.0,
        -31.77825
      ]
    },
    "K3s": {
      "weight": 0.0,
      "played": [
        1.0,
        0.0
      ],
      "evs": [
        0.0,
        -31.29166
      ]
    },
    "K4s": {
      "weight": 0.0,
      "played": [
        1.0,
        0.0
      ],
      "evs": [
        0.0,
        -29.85574
      ]
    },
    "K5s": {
      "weight": 1.0E-4,
      "played": [
        1.0,
        0.0
      ],
      "evs": [
        0.0,
        -29.2082
      ]
    },
    "K6s": {
      "weight": 0.1434,
      "played": [
        1.0,
        0.0
      ],
      "evs": [
        0.0,
        -28.61992
      ]
    },
    "K7s": {
      "weight": 0.0235,
      "played": [
        1.0,
        0.0
      ],
      "evs": [
        0.0,
        -28.27377
      ]
    },
    "K8s": {
      "weight": 0.0071,
      "played": [
        1.0,
        0.0
      ],
      "evs": [
        0.0,
        -28.95019
      ]
    },
    "K9s": {
      "weight": 0.0278,
      "played": [
        1.0,
        0.0
      ],
      "evs": [
        0.0,
        -28.88082
      ]
    },
    "KTs": {
      "weight": 0.4082,
      "played": [
        1.0,
        0.0
      ],
      "evs": [
        0.0,
        -25.0752
      ]
    },
    "KJs": {
      "weight": 0.6458,
      "played": [
        1.0,
        0.0
      ],
      "evs": [
        0.0,
        -25.99283
      ]
    },
    "KQs": {
      "weight": 0.2755,
      "played": [
        1.0,
        0.0
      ],
      "evs": [
        0.0,
        -24.38456
      ]
    },
    "KK": {
      "weight": 0.9677,
      "played": [
        0.0,
        1.0
      ],
      "evs": [
        0.0,
        32.54129
      ]
    },
    "AKo": {
      "weight": 0.5901,
      "played": [
        0.0,
        1.0
      ],
      "evs": [
        0.0,
        2.40369
      ]
    },
    "A2s": {
      "weight": 0.0801,
      "played": [
        1.0,
        0.0
      ],
      "evs": [
        0.0,
        -16.0291
      ]
    },
    "A3s": {
      "weight": 0.1155,
      "played": [
        1.0,
        0.0
      ],
      "evs": [
        0.0,
        -15.18995
      ]
    },
    "A4s": {
      "weight": 0.4696,
      "played": [
        1.0,
        0.0
      ],
      "evs": [
        0.0,
        -15.09115
      ]
    },
    "A5s": {
      "weight": 0.5577,
      "played": [
        1.0,
        0.0
      ],
      "evs": [
        0.0,
        -14.02069
      ]
    },
    "A6s": {
      "weight": 0.0,
      "played": [
        1.0,
        0.0
      ],
      "evs": [
        0.0,
        -16.56496
      ]
    },
    "A7s": {
      "weight": 0.0187,
      "played": [
        1.0,
        0.0
      ],
      "evs": [
        0.0,
        -16.01024
      ]
    },
    "A8s": {
      "weight": 3.0E-4,
      "played": [
        1.0,
        0.0
      ],
      "evs": [
        0.0,
        -16.3213
      ]
    },
    "A9s": {
      "weight": 1.0E-4,
      "played": [
        1.0,
        0.0
      ],
      "evs": [
        0.0,
        -16.44531
      ]
    },
    "ATs": {
      "weight": 0.0018,
      "played": [
        1.0,
        0.0
      ],
      "evs": [
        0.0,
        -15.75105
      ]
    },
    "AJs": {
      "weight": 0.0739,
      "played": [
        1.0,
        0.0
      ],
      "evs": [
        0.0,
        -15.97283
      ]
    },
    "AQs": {
      "weight": 0.0,
      "played": [
        1.0,
        0.0
      ],
      "evs": [
        0.0,
        -14.3406
      ]
    },
    "AKs": {
      "weight": 0.879,
      "played": [
        0.0,
        1.0
      ],
      "evs": [
        0.0,
        8.68191
      ]
    },
    "AA": {
      "weight": 0.999,
      "played": [
        0.0,
        1.0
      ],
      "evs": [
        0.0,
        95.3288
      ]
    }
  }
}